sanic_to_json/INI_helpers.py
sanic_to_json/__init__.py
sanic_to_json/app_helpers.py
sanic_to_json/blueprint_helpers.py
sanic_to_json/generate_json.py
sanic_to_json/schema_helpers.py
sanic_to_json-0.1.9.dist-info/LICENSE
sanic_to_json-0.1.9.dist-info/WHEEL
sanic_to_json-0.1.9.dist-info/METADATA
sanic_to_json-0.1.9.dist-info/RECORD
