Metadata-Version: 2.1
Name: sanic-to-json
Version: 0.1.9
Summary: Create Postman JSON API documentation files from Sanic.
Home-page: https://github.com/caheredia/sanic-to-json
License: MIT
Author: Cristian Heredia
Author-email: cheredia@kountable.com
Requires-Python: >=3.7,<4.0
Classifier: License :: OSI Approved :: MIT License
Classifier: Programming Language :: Python :: 3
Classifier: Programming Language :: Python :: 3.7
Project-URL: Repository, https://github.com/caheredia/sanic-to-json
